mooch/__init__.py
mooch/decorators/__init__.py
mooch/decorators/deprecated.py
mooch/decorators/logging.py
mooch/decorators/retry.py
mooch/decorators/silent.py
mooch/decorators/timeit.py
mooch/decorators/with_lock.py
mooch/location/exceptions.py
mooch/location/location.py
mooch/location/state_abbrev.py
mooch/utils/paths.py
mooch/validators/architecture.py
mooch/validators/command.py
mooch/validators/env_var.py
mooch/validators/operating_system.py
mooch/validators/python_version.py
mooch/validators/virtual_env.py
mooch-2.2.0.dist-info/licenses/LICENSE
mooch-2.2.0.dist-info/METADATA
mooch-2.2.0.dist-info/WHEEL
mooch-2.2.0.dist-info/top_level.txt
mooch-2.2.0.dist-info/RECORD
