Metadata-Version: 2.4
Name: mooch
Version: 2.2.0
Summary: Lightweight Python utility library designed to streamline common development tasks needed for every python project.
Author-email: Nick Stuer <nickstuer@duck.com>
Project-URL: Homepage, https://github.com/nickstuer/mooch
Project-URL: Issues, https://github.com/nickstuer/mooch/issues
Classifier: Development Status :: 5 - Production/Stable
Classifier: Programming Language :: Python :: 3
Classifier: License :: OSI Approved :: MIT License
Classifier: Operating System :: OS Independent
Requires-Python: >=3.9
License-File: LICENSE
Requires-Dist: barnone>=1.0.0
Requires-Dist: packaging>=25.0
Requires-Dist: requests>=2.32.4
Requires-Dist: toml>=0.10.2
Requires-Dist: zettings>=1.0.0
Dynamic: license-file
